MANIFEST.in
README.md
setup.py
sangfor_trans/__init__.py
sangfor_trans/compat.py
sangfor_trans/config.py
sangfor_trans/get_translate.py
sangfor_trans.egg-info/PKG-INFO
sangfor_trans.egg-info/SOURCES.txt
sangfor_trans.egg-info/dependency_links.txt
sangfor_trans.egg-info/top_level.txt
sangfor_trans/baidu_trans/__init__.py
sangfor_trans/baidu_trans/baidu_api.py
sangfor_trans/baidu_trans/setting.py
sangfor_trans/google_trans/__init__.py
sangfor_trans/google_trans/adapters.py
sangfor_trans/google_trans/google_crawl.py
sangfor_trans/google_trans/gtoken.py
sangfor_trans/google_trans/models.py
sangfor_trans/google_trans/urls.py
sangfor_trans/google_trans/utils.py