Metadata-Version: 2.1
Name: sangfor-trans
Version: 0.1.5
Summary: Free Sangfor Translate API with Python. Translates totally free of charge.
Home-page: https://github.com/Scoefield/SangforTrans
Author: scoefield
Author-email: scoefield@163.com
License: MIT
Keywords: sangfor translate translator
Platform: UNKNOWN
Classifier: Development Status :: 5 - Production/Stable
Classifier: Intended Audience :: Education
Classifier: Intended Audience :: End Users/Desktop
Classifier: License :: Freeware
Classifier: Operating System :: POSIX
Classifier: Operating System :: Microsoft :: Windows
Classifier: Operating System :: MacOS :: MacOS X
Classifier: Topic :: Education
Classifier: Programming Language :: Python :: 2.7
Classifier: Programming Language :: Python :: 3.4
Classifier: Programming Language :: Python :: 3.5
Classifier: Programming Language :: Python :: 3.6
